[{"date": "20240116", "views": 10265}, {"date": "20240117", "views": 8985}, {"date": "20240118", "views": 15169}, {"date": "20240119", "views": 10226}, {"date": "20240120", "views": 7318}, {"date": "20240121", "views": 7230}, {"date": "20240122", "views": 7111}, {"date": "20240123", "views": 7400}, {"date": "20240124", "views": 10100}, {"date": "20240125", "views": 7322}, {"date": "20240126", "views": 10946}, {"date": "20240127", "views": 6771}, {"date": "20240128", "views": 6308}, {"date": "20240129", "views": 7427}, {"date": "20240130", "views": 17998}, {"date": "20240131", "views": 7187}, {"date": "20240201", "views": 10899}, {"date": "20240202", "views": 7111}, {"date": "20240203", "views": 8632}, {"date": "20240204", "views": 5542}, {"date": "20240205", "views": 6636}, {"date": "20240206", "views": 6672}, {"date": "20240207", "views": 6920}, {"date": "20240208", "views": 7180}, {"date": "20240209", "views": 8274}, {"date": "20240210", "views": 5677}, {"date": "20240211", "views": 8224}, {"date": "20240212", "views": 6014}, {"date": "20240213", "views": 7040}, {"date": "20240214", "views": 6336}, {"date": "20240215", "views": 6408}, {"date": "20240216", "views": 5932}, {"date": "20240217", "views": 18220}, {"date": "20240218", "views": 17280}, {"date": "20240219", "views": 9045}, {"date": "20240220", "views": 6425}, {"date": "20240221", "views": 6808}, {"date": "20240222", "views": 6196}, {"date": "20240223", "views": 5930}, {"date": "20240224", "views": 4884}, {"date": "20240225", "views": 8173}, {"date": "20240226", "views": 6252}, {"date": "20240227", "views": 7895}, {"date": "20240228", "views": 6267}, {"date": "20240229", "views": 6309}, {"date": "20240301", "views": 6115}, {"date": "20240302", "views": 5181}, {"date": "20240303", "views": 5556}, {"date": "20240304", "views": 7962}, {"date": "20240305", "views": 7236}, {"date": "20240306", "views": 9572}, {"date": "20240307", "views": 7082}, {"date": "20240308", "views": 6749}, {"date": "20240309", "views": 5201}, {"date": "20240310", "views": 4635}, {"date": "20240311", "views": 4925}, {"date": "20240312", "views": 8709}, {"date": "20240313", "views": 5581}, {"date": "20240314", "views": 7573}, {"date": "20240315", "views": 5344}, {"date": "20240316", "views": 4023}]